{
  "total_operations": 1,
  "successful_operations": 1,
  "failed_operations": 0,
  "start_time": "2025-07-18T14:49:48.774924",
  "end_time": "2025-07-18T14:50:24.268248",
  "operation_latencies": [
    35.49306583404541
  ],
  "total_records_processed": 256869,
  "total_bytes_processed": 50095399,
  "files_created": 14,
  "api_calls_made": 14,
  "peak_memory_mb": null,
  "avg_cpu_percent": null,
  "disk_io_read_mb": null,
  "disk_io_write_mb": null,
  "error_messages": [],
  "retry_attempts": 0,
  "operation_name": "ApiExtractStep.eia_extract_year_optimized",
  "benchmark_version": "1.0"
}