{
  "total_operations": 1,
  "successful_operations": 1,
  "failed_operations": 0,
  "start_time": "2025-07-17T16:20:55.901560",
  "end_time": "2025-07-17T16:21:05.956032",
  "operation_latencies": [
    10.05422306060791
  ],
  "total_records_processed": 2249787,
  "total_bytes_processed": 11691575,
  "files_created": 1,
  "api_calls_made": 0,
  "peak_memory_mb": null,
  "avg_cpu_percent": null,
  "disk_io_read_mb": null,
  "disk_io_write_mb": null,
  "error_messages": [],
  "retry_attempts": 0,
  "operation_name": "DataCleanerStep.eia_transform_2024",
  "benchmark_version": "1.0"
}